{
  "url": "https://www.birthdaycakecandle.com/dinner-candle",
  "title": "Dinner Candle - Sunwing Technology",
  "description": "A dinner candle is a classic choice for adding warmth and sophistication to any meal. Typically unscented and designed to burn cleanly, these candles are perfec",
  "captured_at": "2026-03-09T00:25:43.391484",
  "links_count": 21,
  "discovered_resources_count": 25,
  "resources_count": 21,
  "interaction_clicked_count": 0,
  "api_samples_count": 0,
  "directory": "015_dinner-candle_ff6a5194"
}